bloomf/__init__.py
bloomf/main.py
bloomf/test.py
bloomf-0.3.dist-info/METADATA
bloomf-0.3.dist-info/RECORD
bloomf-0.3.dist-info/WHEEL
bloomf-0.3.dist-info/top_level.txt
