Metadata-Version: 2.1
Name: bloomf
Version: 0.3
Summary: Simple Bloom Filter implmentation in Python
Home-page: https://github.com/sambhav2612/karumanchi/tree/master/bloom-filter
Author: Sambhav Jain
Author-email: sambhavjain2612@gmail.com
License: UNKNOWN
Platform: UNKNOWN
Classifier: Programming Language :: Python :: 3
Classifier: License :: OSI Approved :: GNU General Public License v3 (GPLv3)
Classifier: Operating System :: OS Independent
